{
  "version": "5.1.1",
  "flags": {},
  "shapes": [
    {
      "label": "pore",
      "points": [
        [
          666,
          133
        ],
        [
          676,
          139
        ]
      ],
      "group_id": "null",
      "shape_type": "rectangle",
      "flags": {}
    },
    {
      "label": "pore",
      "points": [
        [
          680,
          131
        ],
        [
          695,
          141
        ]
      ],
      "group_id": "null",
      "shape_type": "rectangle",
      "flags": {}
    },
    {
      "label": "pore",
      "points": [
        [
          689,
          104
        ],
        [
          704,
          120
        ]
      ],
      "group_id": "null",
      "shape_type": "rectangle",
      "flags": {}
    },
    {
      "label": "pore",
      "points": [
        [
          710,
          106
        ],
        [
          726,
          126
        ]
      ],
      "group_id": "null",
      "shape_type": "rectangle",
      "flags": {}
    },
    {
      "label": "pore",
      "points": [
        [
          736,
          58
        ],
        [
          746,
          70
        ]
      ],
      "group_id": "null",
      "shape_type": "rectangle",
      "flags": {}
    },
    {
      "label": "pore",
      "points": [
        [
          731,
          68
        ],
        [
          745,
          86
        ]
      ],
      "group_id": "null",
      "shape_type": "rectangle",
      "flags": {}
    },
    {
      "label": "pore",
      "points": [
        [
          726,
          44
        ],
        [
          739,
          63
        ]
      ],
      "group_id": "null",
      "shape_type": "rectangle",
      "flags": {}
    },
    {
      "label": "discontinuity",
      "points": [
        [
          719,
          16
        ],
        [
          771,
          129
        ]
      ],
      "group_id": "null",
      "shape_type": "rectangle",
      "flags": {}
    },
    {
      "label": "discontinuity",
      "points": [
        [
          0,
          114
        ],
        [
          62,
          166
        ]
      ],
      "group_id": "null",
      "shape_type": "rectangle",
      "flags": {}
    },
    {
      "label": "deposit",
      "points": [
        [
          136,
          32
        ],
        [
          232,
          128
        ]
      ],
      "group_id": "null",
      "shape_type": "rectangle",
      "flags": {}
    },
    {
      "label": "discontinuity",
      "points": [
        [
          341,
          32
        ],
        [
          381,
          64
        ]
      ],
      "group_id": "null",
      "shape_type": "rectangle",
      "flags": {}
    },
    {
      "label": "deposit",
      "points": [
        [
          272,
          59
        ],
        [
          321,
          102
        ]
      ],
      "group_id": "null",
      "shape_type": "rectangle",
      "flags": {}
    },
    {
      "label": "stain",
      "points": [
        [
          416,
          94
        ],
        [
          433,
          104
        ]
      ],
      "group_id": "null",
      "shape_type": "rectangle",
      "flags": {}
    },
    {
      "label": "stain",
      "points": [
        [
          529,
          29
        ],
        [
          604,
          95
        ]
      ],
      "group_id": "null",
      "shape_type": "rectangle",
      "flags": {}
    },
    {
      "label": "stain",
      "points": [
        [
          617,
          44
        ],
        [
          632,
          69
        ]
      ],
      "group_id": "null",
      "shape_type": "rectangle",
      "flags": {}
    },
    {
      "label": "stain",
      "points": [
        [
          599,
          82
        ],
        [
          623,
          99
        ]
      ],
      "group_id": "null",
      "shape_type": "rectangle",
      "flags": {}
    }
  ],
  "imagePath": "25_195",
  "imageData": "",
  "imageHeight": 176,
  "imageWidth": 784
}